pyevsim/__init__.py
pyevsim/behavior_model.py
pyevsim/behavior_model_executor.py
pyevsim/default_message_catcher.py
pyevsim/definition.py
pyevsim/gen.py
pyevsim/structural_model.py
pyevsim/system_executor.py
pyevsim/system_message.py
pyevsim/system_object.py
pyevsim/system_simulator.py
pyevsim/termination_manager.py
pyevsim-1.1.7.dist-info/LICENSE
pyevsim-1.1.7.dist-info/METADATA
pyevsim-1.1.7.dist-info/WHEEL
pyevsim-1.1.7.dist-info/top_level.txt
pyevsim-1.1.7.dist-info/RECORD
