Metadata-Version: 2.1
Name: pyevsim
Version: 1.1.7
Summary: A library that provides a Modeling & Simulation Environment for Discrete Event System Formalism
Home-page: https://github.com/eventsim/pyevsim
Author: Changbeom Choi
Author-email: me@cbchoi.info
License: MIT
Platform: UNKNOWN
Classifier: Programming Language :: Python :: 3
Classifier: License :: OSI Approved :: MIT License
Classifier: Operating System :: OS Independent
